ttkDesigner/__init__.py
ttkDesigner/__main__.py
ttkDesigner/app/__init__.py
ttkDesigner/app/about.py
ttkDesigner/app/cfg.py
ttkDesigner/app/designer.py
ttkDesigner/app/main.py
ttkDesigner/app/menuBarEditor.py
ttkDesigner/app/notepad.py
ttkDesigner/app/propertyeditor.py
ttkDesigner/app/quickexport.py
ttkDesigner/app/signalsloteditor.py
ttkDesigner/app/treeinspector.py
ttkDesigner/app/widgetbox.py
ttkDesigner/app/windoweditor.py
ttkDesigner/app/superobj/__init__.py
ttkDesigner/app/superobj/supercontrol.py
ttkDesigner/app/superobj/superlayout.py
ttkDesigner/app/superobj/superlayoutgrid.py
ttkDesigner/app/superobj/superlayouthbox.py
ttkDesigner/app/superobj/superlayoutvbox.py
ttkDesigner/app/superobj/superobj.py
ttkDesigner/app/superobj/superwidget.py
ttkDesigner/app/superobj/superwidgetabstractscrollarea.py
ttkDesigner/app/superobj/superwidgetcontainer.py
ttkDesigner/app/superobj/superwidgetframe.py
ttkDesigner/app/superobj/superwidgetlist.py
ttkDesigner/app/superobj/superwidgetmenubutton.py
ttkDesigner/app/superobj/superwidgetradiobutton.py
ttkDesigner/app/superobj/superwidgetsplitter.py
ttkDesigner/app/superobj/superwidgettextedit.py
ttkDesigner/tui/menuBarEditor.tui.json
ttkDesigner/tui/newWindow.tui.json
ttkDesigner/tui/quickExport.tui.json
ttkDesigner/tui/quickImport.tui.json
ttkdesigner-0.48.2a0.dist-info/METADATA
ttkdesigner-0.48.2a0.dist-info/WHEEL
ttkdesigner-0.48.2a0.dist-info/entry_points.txt
ttkdesigner-0.48.2a0.dist-info/top_level.txt
ttkdesigner-0.48.2a0.dist-info/RECORD
